vistudio/__init__.py
vistudio/annotation/__init__.py
vistudio/annotation/api/__init__.py
vistudio/annotation/api/annotation.py
vistudio/annotation/client/__init__.py
vistudio/annotation/client/annotation_client.py
vistudio/annotation/config/__init__.py
vistudio/annotation/config/arg_parser.py
vistudio/annotation/config/config.py
vistudio/annotation/datasource/__init__.py
vistudio/annotation/datasource/image_datasource.py
vistudio/annotation/datasource/mongo_query_pipeline.py
vistudio/annotation/datasource/sharded_mongo_datasource.py
vistudio/annotation/datasource/xml_datasource.py
vistudio/annotation/operator/__init__.py
vistudio/annotation/operator/annotation_state_updater.py
vistudio/annotation/operator/cityscapes_formatter.py
vistudio/annotation/operator/coco_formatter.py
vistudio/annotation/operator/cvat_formatter.py
vistudio/annotation/operator/filter.py
vistudio/annotation/operator/image_created_at_updater.py
vistudio/annotation/operator/image_formatter.py
vistudio/annotation/operator/imagenet_formatter.py
vistudio/annotation/operator/label_formatter.py
vistudio/annotation/operator/paddleclas_formatter.py
vistudio/annotation/operator/paddleseg_formatter.py
vistudio/annotation/operator/reader.py
vistudio/annotation/operator/thumbnail_generator.py
vistudio/annotation/operator/thumbnail_state_updater.py
vistudio/annotation/operator/vistudio_formatter.py
vistudio/annotation/operator/webp_generator.py
vistudio/annotation/operator/webp_state_updater.py
vistudio/annotation/operator/zip_formatter.py
vistudio/annotation/pipeline/__init__.py
vistudio/annotation/pipeline/base_export_pipeline.py
vistudio/annotation/pipeline/base_import_pipeline.py
vistudio/annotation/pipeline/export_coco_pipeline.py
vistudio/annotation/pipeline/export_paddleclas_pipeline.py
vistudio/annotation/pipeline/export_paddleseg_pipeline.py
vistudio/annotation/pipeline/generate_thumbnail_pipeline.py
vistudio/annotation/pipeline/generate_webp_pipeline.py
vistudio-1.0.1.10.dist-info/METADATA
vistudio-1.0.1.10.dist-info/WHEEL
vistudio-1.0.1.10.dist-info/top_level.txt
vistudio-1.0.1.10.dist-info/RECORD
